mofpy/__init__.py
mofpy/py.typed
mofpy/structure/__init__.py
mofpy/structure/analysis/__init__.py
mofpy/structure/construct/__init__.py
mofpy/utils/__init__.py
mofpy/utils/io_structure.py
mofpy-0.0.0.dist-info/LICENSE
mofpy-0.0.0.dist-info/METADATA
mofpy-0.0.0.dist-info/WHEEL
mofpy-0.0.0.dist-info/RECORD
